crystal_torture-1.2.0.dist-info/RECORD
crystal_torture-1.2.0.dist-info/WHEEL
crystal_torture-1.2.0.dist-info/METADATA
crystal_torture/libdist.cpython-310-darwin.so
crystal_torture/version.py
crystal_torture/tort.py
crystal_torture/graph.py
crystal_torture/__init__.py
crystal_torture/_tort.cpython-310-darwin.so
crystal_torture/cluster.py
crystal_torture/pymatgen_interface.py
crystal_torture/pymatgen_doping.py
crystal_torture/exceptions.py
crystal_torture/node.py
crystal_torture/minimal_cluster.py
crystal_torture/dist.py
crystal_torture/.dylibs/libgfortran.5.dylib
crystal_torture/.dylibs/libquadmath.0.dylib
crystal_torture/.dylibs/libgcc_s.1.1.dylib
crystal_torture/.dylibs/libgomp.1.dylib
