Metadata-Version: 2.1
Name: crystal-torture
Version: 1.2.0
Summary: Crystal Tortuosity Analysis with Fortran Extensions
Keywords: crystallography,materials science,tortuosity,percolation,fortran,scientific computing
Author-Email: Conn O'Rourke <conn.orourke@gmail.com>
License: MIT
Classifier: Development Status :: 5 - Production/Stable
Classifier: Intended Audience :: Science/Research
Classifier: License :: OSI Approved :: MIT License
Classifier: Operating System :: OS Independent
Classifier: Programming Language :: Python :: 3
Classifier: Programming Language :: Python :: 3.10
Classifier: Programming Language :: Python :: 3.11
Classifier: Programming Language :: Python :: 3.12
Classifier: Programming Language :: Python :: 3.13
Classifier: Programming Language :: Fortran
Classifier: Topic :: Scientific/Engineering :: Chemistry
Classifier: Topic :: Scientific/Engineering :: Physics
Classifier: Topic :: Scientific/Engineering :: Mathematics
Project-URL: Homepage, https://github.com/connorourke/crystal_torture
Project-URL: Repository, https://github.com/connorourke/crystal_torture
Project-URL: Documentation, https://github.com/connorourke/crystal_torture
Project-URL: Bug Tracker, https://github.com/connorourke/crystal_torture/issues
Project-URL: Changelog, https://github.com/connorourke/crystal_torture/releases
Requires-Python: >=3.10
Requires-Dist: numpy>=1.19.0
Requires-Dist: pymatgen>=2022.0.0
Provides-Extra: dev
Requires-Dist: pytest>=6.0; extra == "dev"
Requires-Dist: pytest-cov; extra == "dev"
Requires-Dist: coverage; extra == "dev"
Requires-Dist: ddt; extra == "dev"
Requires-Dist: meson; extra == "dev"
Requires-Dist: ninja; extra == "dev"
Provides-Extra: docs
Requires-Dist: Sphinx>=4.0.0; extra == "docs"
Requires-Dist: myst-parser>=0.18.0; extra == "docs"
Requires-Dist: myst-nb>=0.17.0; extra == "docs"
Requires-Dist: alabaster; extra == "docs"
Requires-Dist: sphinxcontrib-websupport; extra == "docs"
